[
        {
                "id": "1",
                "project_title": "project_title 1",
                "workflow_type": "workflow_type 1",
                "created_by": "created_by 1",
                "description": "description 1",
                "created_at": "created_at 1",
                "project_type": "project_type 1",
                "developers": []
        },
        {
                "id": "2",
                "project_title": "project_title 2",
                "workflow_type": "workflow_type 2",
                "created_by": "created_by 2",
                "description": "description 2",
                "created_at": "created_at 2",
                "project_type": "project_type 2",
                "developers": []
        },
        {
                "id": "3",
                "project_title": "project_title 3",
                "workflow_type": "workflow_type 3",
                "created_by": "created_by 3",
                "description": "description 3",
                "created_at": "created_at 3",
                "project_type": "project_type 3",
                "developers": []
        },
        {
                "id": "4",
                "project_title": "project_title 4",
                "workflow_type": "workflow_type 4",
                "created_by": "created_by 4",
                "description": "description 4",
                "created_at": "created_at 4",
                "project_type": "project_type 4",
                "developers": []
        },
        {
                "id": "5",
                "project_title": "project_title 5",
                "workflow_type": "workflow_type 5",
                "created_by": "created_by 5",
                "description": "description 5",
                "created_at": "created_at 5",
                "project_type": "project_type 5",
                "developers": []
        },
        {
                "id": "6",
                "project_title": "project_title 6",
                "workflow_type": "workflow_type 6",
                "created_by": "created_by 6",
                "description": "description 6",
                "created_at": "created_at 6",
                "project_type": "project_type 6",
                "developers": []
        },
        {
                "id": "7",
                "project_title": "project_title 7",
                "workflow_type": "workflow_type 7",
                "created_by": "created_by 7",
                "description": "description 7",
                "created_at": "created_at 7",
                "project_type": "project_type 7",
                "developers": []
        },
        {
                "id": "8",
                "project_title": "project_title 8",
                "workflow_type": "workflow_type 8",
                "created_by": "created_by 8",
                "description": "description 8",
                "created_at": "created_at 8",
                "project_type": "project_type 8",
                "developers": []
        },
        {
                "id": "9",
                "project_title": "project_title 9",
                "workflow_type": "workflow_type 9",
                "created_by": "created_by 9",
                "description": "description 9",
                "created_at": "created_at 9",
                "project_type": "project_type 9",
                "developers": []
        },
        {
                "id": "10",
                "project_title": "project_title 10",
                "workflow_type": "workflow_type 10",
                "created_by": "created_by 10",
                "description": "description 10",
                "created_at": "created_at 10",
                "project_type": "project_type 10",
                "developers": []
        },
        {
                "id": "11",
                "project_title": "project_title 11",
                "workflow_type": "workflow_type 11",
                "created_by": "created_by 11",
                "description": "description 11",
                "created_at": "created_at 11",
                "project_type": "project_type 11",
                "developers": []
        },
        {
                "id": "12",
                "project_title": "project_title 12",
                "workflow_type": "workflow_type 12",
                "created_by": "created_by 12",
                "description": "description 12",
                "created_at": "created_at 12",
                "project_type": "project_type 12",
                "developers": []
        },
        {
                "id": "13",
                "project_title": "project_title 13",
                "workflow_type": "workflow_type 13",
                "created_by": "created_by 13",
                "description": "description 13",
                "created_at": "created_at 13",
                "project_type": "project_type 13",
                "developers": []
        },
        {
                "id": "14",
                "project_title": "project_title 14",
                "workflow_type": "workflow_type 14",
                "created_by": "created_by 14",
                "description": "description 14",
                "created_at": "created_at 14",
                "project_type": "project_type 14",
                "developers": []
        },
        {
                "id": "15",
                "project_title": "project_title 15",
                "workflow_type": "workflow_type 15",
                "created_by": "created_by 15",
                "description": "description 15",
                "created_at": "created_at 15",
                "project_type": "project_type 15",
                "developers": []
        },
        {
                "id": "16",
                "project_title": "project_title 16",
                "workflow_type": "workflow_type 16",
                "created_by": "created_by 16",
                "description": "description 16",
                "created_at": "created_at 16",
                "project_type": "project_type 16",
                "developers": []
        },
        {
                "id": "17",
                "project_title": "project_title 17",
                "workflow_type": "workflow_type 17",
                "created_by": "created_by 17",
                "description": "description 17",
                "created_at": "created_at 17",
                "project_type": "project_type 17",
                "developers": []
        },
        {
                "id": "18",
                "project_title": "project_title 18",
                "workflow_type": "workflow_type 18",
                "created_by": "created_by 18",
                "description": "description 18",
                "created_at": "created_at 18",
                "project_type": "project_type 18",
                "developers": []
        },
        {
                "id": "19",
                "project_title": "project_title 19",
                "workflow_type": "workflow_type 19",
                "created_by": "created_by 19",
                "description": "description 19",
                "created_at": "created_at 19",
                "project_type": "project_type 19",
                "developers": []
        },
        {
                "id": "20",
                "project_title": "project_title 20",
                "workflow_type": "workflow_type 20",
                "created_by": "created_by 20",
                "description": "description 20",
                "created_at": "created_at 20",
                "project_type": "project_type 20",
                "developers": []
        },
        {
                "id": "21",
                "project_title": "project_title 21",
                "workflow_type": "workflow_type 21",
                "created_by": "created_by 21",
                "description": "description 21",
                "created_at": "created_at 21",
                "project_type": "project_type 21",
                "developers": []
        },
        {
                "id": "22",
                "project_title": "project_title 22",
                "workflow_type": "workflow_type 22",
                "created_by": "created_by 22",
                "description": "description 22",
                "created_at": "created_at 22",
                "project_type": "project_type 22",
                "developers": []
        },
        {
                "id": "23",
                "project_title": "project_title 23",
                "workflow_type": "workflow_type 23",
                "created_by": "created_by 23",
                "description": "description 23",
                "created_at": "created_at 23",
                "project_type": "project_type 23",
                "developers": []
        },
        {
                "id": "24",
                "project_title": "project_title 24",
                "workflow_type": "workflow_type 24",
                "created_by": "created_by 24",
                "description": "description 24",
                "created_at": "created_at 24",
                "project_type": "project_type 24",
                "developers": []
        },
        {
                "id": "25",
                "project_title": "project_title 25",
                "workflow_type": "workflow_type 25",
                "created_by": "created_by 25",
                "description": "description 25",
                "created_at": "created_at 25",
                "project_type": "project_type 25",
                "developers": []
        },
        {
                "id": "26",
                "project_title": "project_title 26",
                "workflow_type": "workflow_type 26",
                "created_by": "created_by 26",
                "description": "description 26",
                "created_at": "created_at 26",
                "project_type": "project_type 26",
                "developers": []
        },
        {
                "id": "27",
                "project_title": "project_title 27",
                "workflow_type": "workflow_type 27",
                "created_by": "created_by 27",
                "description": "description 27",
                "created_at": "created_at 27",
                "project_type": "project_type 27",
                "developers": []
        },
        {
                "id": "28",
                "project_title": "project_title 28",
                "workflow_type": "workflow_type 28",
                "created_by": "created_by 28",
                "description": "description 28",
                "created_at": "created_at 28",
                "project_type": "project_type 28",
                "developers": []
        },
        {
                "id": "29",
                "project_title": "project_title 29",
                "workflow_type": "workflow_type 29",
                "created_by": "created_by 29",
                "description": "description 29",
                "created_at": "created_at 29",
                "project_type": "project_type 29",
                "developers": []
        },
        {
                "id": "30",
                "project_title": "project_title 30",
                "workflow_type": "workflow_type 30",
                "created_by": "created_by 30",
                "description": "description 30",
                "created_at": "created_at 30",
                "project_type": "project_type 30",
                "developers": []
        },
        {
                "id": "31",
                "project_title": "project_title 31",
                "workflow_type": "workflow_type 31",
                "created_by": "created_by 31",
                "description": "description 31",
                "created_at": "created_at 31",
                "project_type": "project_type 31",
                "developers": []
        },
        {
                "id": "32",
                "project_title": "project_title 32",
                "workflow_type": "workflow_type 32",
                "created_by": "created_by 32",
                "description": "description 32",
                "created_at": "created_at 32",
                "project_type": "project_type 32",
                "developers": []
        },
        {
                "id": "33",
                "project_title": "project_title 33",
                "workflow_type": "workflow_type 33",
                "created_by": "created_by 33",
                "description": "description 33",
                "created_at": "created_at 33",
                "project_type": "project_type 33",
                "developers": []
        },
        {
                "id": "34",
                "project_title": "project_title 34",
                "workflow_type": "workflow_type 34",
                "created_by": "created_by 34",
                "description": "description 34",
                "created_at": "created_at 34",
                "project_type": "project_type 34",
                "developers": []
        },
        {
                "id": "35",
                "project_title": "project_title 35",
                "workflow_type": "workflow_type 35",
                "created_by": "created_by 35",
                "description": "description 35",
                "created_at": "created_at 35",
                "project_type": "project_type 35",
                "developers": []
        },
        {
                "id": "36",
                "project_title": "project_title 36",
                "workflow_type": "workflow_type 36",
                "created_by": "created_by 36",
                "description": "description 36",
                "created_at": "created_at 36",
                "project_type": "project_type 36",
                "developers": []
        },
        {
                "id": "37",
                "project_title": "project_title 37",
                "workflow_type": "workflow_type 37",
                "created_by": "created_by 37",
                "description": "description 37",
                "created_at": "created_at 37",
                "project_type": "project_type 37",
                "developers": []
        },
        {
                "id": "38",
                "project_title": "project_title 38",
                "workflow_type": "workflow_type 38",
                "created_by": "created_by 38",
                "description": "description 38",
                "created_at": "created_at 38",
                "project_type": "project_type 38",
                "developers": []
        },
        {
                "id": "39",
                "project_title": "project_title 39",
                "workflow_type": "workflow_type 39",
                "created_by": "created_by 39",
                "description": "description 39",
                "created_at": "created_at 39",
                "project_type": "project_type 39",
                "developers": []
        },
        {
                "id": "40",
                "project_title": "project_title 40",
                "workflow_type": "workflow_type 40",
                "created_by": "created_by 40",
                "description": "description 40",
                "created_at": "created_at 40",
                "project_type": "project_type 40",
                "developers": []
        },
        {
                "id": "41",
                "project_title": "project_title 41",
                "workflow_type": "workflow_type 41",
                "created_by": "created_by 41",
                "description": "description 41",
                "created_at": "created_at 41",
                "project_type": "project_type 41",
                "developers": []
        },
        {
                "id": "42",
                "project_title": "project_title 42",
                "workflow_type": "workflow_type 42",
                "created_by": "created_by 42",
                "description": "description 42",
                "created_at": "created_at 42",
                "project_type": "project_type 42",
                "developers": []
        },
        {
                "id": "43",
                "project_title": "project_title 43",
                "workflow_type": "workflow_type 43",
                "created_by": "created_by 43",
                "description": "description 43",
                "created_at": "created_at 43",
                "project_type": "project_type 43",
                "developers": []
        },
        {
                "id": "44",
                "project_title": "project_title 44",
                "workflow_type": "workflow_type 44",
                "created_by": "created_by 44",
                "description": "description 44",
                "created_at": "created_at 44",
                "project_type": "project_type 44",
                "developers": []
        },
        {
                "id": "45",
                "project_title": "project_title 45",
                "workflow_type": "workflow_type 45",
                "created_by": "created_by 45",
                "description": "description 45",
                "created_at": "created_at 45",
                "project_type": "project_type 45",
                "developers": []
        },
        {
                "id": "46",
                "project_title": "project_title 46",
                "workflow_type": "workflow_type 46",
                "created_by": "created_by 46",
                "description": "description 46",
                "created_at": "created_at 46",
                "project_type": "project_type 46",
                "developers": []
        },
        {
                "id": "47",
                "project_title": "project_title 47",
                "workflow_type": "workflow_type 47",
                "created_by": "created_by 47",
                "description": "description 47",
                "created_at": "created_at 47",
                "project_type": "project_type 47",
                "developers": []
        },
        {
                "id": "48",
                "project_title": "project_title 48",
                "workflow_type": "workflow_type 48",
                "created_by": "created_by 48",
                "description": "description 48",
                "created_at": "created_at 48",
                "project_type": "project_type 48",
                "developers": []
        },
        {
                "id": "49",
                "project_title": "project_title 49",
                "workflow_type": "workflow_type 49",
                "created_by": "created_by 49",
                "description": "description 49",
                "created_at": "created_at 49",
                "project_type": "project_type 49",
                "developers": []
        },
        {
                "id": "50",
                "project_title": "project_title 50",
                "workflow_type": "workflow_type 50",
                "created_by": "created_by 50",
                "description": "description 50",
                "created_at": "created_at 50",
                "project_type": "project_type 50",
                "developers": []
        },
        {
                "id": "51",
                "project_title": "project_title 51",
                "workflow_type": "workflow_type 51",
                "created_by": "created_by 51",
                "description": "description 51",
                "created_at": "created_at 51",
                "project_type": "project_type 51",
                "developers": []
        },
        {
                "id": "52",
                "project_title": "project_title 52",
                "workflow_type": "workflow_type 52",
                "created_by": "created_by 52",
                "description": "description 52",
                "created_at": "created_at 52",
                "project_type": "project_type 52",
                "developers": []
        },
        {
                "id": "53",
                "project_title": "project_title 53",
                "workflow_type": "workflow_type 53",
                "created_by": "created_by 53",
                "description": "description 53",
                "created_at": "created_at 53",
                "project_type": "project_type 53",
                "developers": []
        },
        {
                "id": "54",
                "project_title": "project_title 54",
                "workflow_type": "workflow_type 54",
                "created_by": "created_by 54",
                "description": "description 54",
                "created_at": "created_at 54",
                "project_type": "project_type 54",
                "developers": []
        },
        {
                "id": "55",
                "project_title": "project_title 55",
                "workflow_type": "workflow_type 55",
                "created_by": "created_by 55",
                "description": "description 55",
                "created_at": "created_at 55",
                "project_type": "project_type 55",
                "developers": []
        },
        {
                "id": "56",
                "project_title": "project_title 56",
                "workflow_type": "workflow_type 56",
                "created_by": "created_by 56",
                "description": "description 56",
                "created_at": "created_at 56",
                "project_type": "project_type 56",
                "developers": []
        },
        {
                "id": "57",
                "project_title": "project_title 57",
                "workflow_type": "workflow_type 57",
                "created_by": "created_by 57",
                "description": "description 57",
                "created_at": "created_at 57",
                "project_type": "project_type 57",
                "developers": []
        },
        {
                "id": "58",
                "project_title": "project_title 58",
                "workflow_type": "workflow_type 58",
                "created_by": "created_by 58",
                "description": "description 58",
                "created_at": "created_at 58",
                "project_type": "project_type 58",
                "developers": []
        },
        {
                "id": "59",
                "project_title": "project_title 59",
                "workflow_type": "workflow_type 59",
                "created_by": "created_by 59",
                "description": "description 59",
                "created_at": "created_at 59",
                "project_type": "project_type 59",
                "developers": []
        },
        {
                "id": "60",
                "project_title": "project_title 60",
                "workflow_type": "workflow_type 60",
                "created_by": "created_by 60",
                "description": "description 60",
                "created_at": "created_at 60",
                "project_type": "project_type 60",
                "developers": []
        },
        {
                "id": "61",
                "project_title": "project_title 61",
                "workflow_type": "workflow_type 61",
                "created_by": "created_by 61",
                "description": "description 61",
                "created_at": "created_at 61",
                "project_type": "project_type 61",
                "developers": []
        },
        {
                "id": "62",
                "project_title": "project_title 62",
                "workflow_type": "workflow_type 62",
                "created_by": "created_by 62",
                "description": "description 62",
                "created_at": "created_at 62",
                "project_type": "project_type 62",
                "developers": []
        },
        {
                "id": "63",
                "project_title": "project_title 63",
                "workflow_type": "workflow_type 63",
                "created_by": "created_by 63",
                "description": "description 63",
                "created_at": "created_at 63",
                "project_type": "project_type 63",
                "developers": []
        },
        {
                "id": "64",
                "project_title": "project_title 64",
                "workflow_type": "workflow_type 64",
                "created_by": "created_by 64",
                "description": "description 64",
                "created_at": "created_at 64",
                "project_type": "project_type 64",
                "developers": []
        },
        {
                "id": "65",
                "project_title": "project_title 65",
                "workflow_type": "workflow_type 65",
                "created_by": "created_by 65",
                "description": "description 65",
                "created_at": "created_at 65",
                "project_type": "project_type 65",
                "developers": []
        },
        {
                "id": "66",
                "project_title": "project_title 66",
                "workflow_type": "workflow_type 66",
                "created_by": "created_by 66",
                "description": "description 66",
                "created_at": "created_at 66",
                "project_type": "project_type 66",
                "developers": []
        },
        {
                "id": "67",
                "project_title": "project_title 67",
                "workflow_type": "workflow_type 67",
                "created_by": "created_by 67",
                "description": "description 67",
                "created_at": "created_at 67",
                "project_type": "project_type 67",
                "developers": []
        },
        {
                "id": "68",
                "project_title": "project_title 68",
                "workflow_type": "workflow_type 68",
                "created_by": "created_by 68",
                "description": "description 68",
                "created_at": "created_at 68",
                "project_type": "project_type 68",
                "developers": []
        },
        {
                "id": "69",
                "project_title": "project_title 69",
                "workflow_type": "workflow_type 69",
                "created_by": "created_by 69",
                "description": "description 69",
                "created_at": "created_at 69",
                "project_type": "project_type 69",
                "developers": []
        },
        {
                "id": "70",
                "project_title": "project_title 70",
                "workflow_type": "workflow_type 70",
                "created_by": "created_by 70",
                "description": "description 70",
                "created_at": "created_at 70",
                "project_type": "project_type 70",
                "developers": []
        },
        {
                "id": "71",
                "project_title": "project_title 71",
                "workflow_type": "workflow_type 71",
                "created_by": "created_by 71",
                "description": "description 71",
                "created_at": "created_at 71",
                "project_type": "project_type 71",
                "developers": []
        },
        {
                "id": "72",
                "project_title": "project_title 72",
                "workflow_type": "workflow_type 72",
                "created_by": "created_by 72",
                "description": "description 72",
                "created_at": "created_at 72",
                "project_type": "project_type 72",
                "developers": []
        },
        {
                "id": "73",
                "project_title": "project_title 73",
                "workflow_type": "workflow_type 73",
                "created_by": "created_by 73",
                "description": "description 73",
                "created_at": "created_at 73",
                "project_type": "project_type 73",
                "developers": []
        },
        {
                "id": "74",
                "project_title": "project_title 74",
                "workflow_type": "workflow_type 74",
                "created_by": "created_by 74",
                "description": "description 74",
                "created_at": "created_at 74",
                "project_type": "project_type 74",
                "developers": []
        },
        {
                "id": "75",
                "project_title": "project_title 75",
                "workflow_type": "workflow_type 75",
                "created_by": "created_by 75",
                "description": "description 75",
                "created_at": "created_at 75",
                "project_type": "project_type 75",
                "developers": []
        },
        {
                "id": "76",
                "project_title": "project_title 76",
                "workflow_type": "workflow_type 76",
                "created_by": "created_by 76",
                "description": "description 76",
                "created_at": "created_at 76",
                "project_type": "project_type 76",
                "developers": []
        },
        {
                "id": "77",
                "project_title": "project_title 77",
                "workflow_type": "workflow_type 77",
                "created_by": "created_by 77",
                "description": "description 77",
                "created_at": "created_at 77",
                "project_type": "project_type 77",
                "developers": []
        },
        {
                "id": "78",
                "project_title": "project_title 78",
                "workflow_type": "workflow_type 78",
                "created_by": "created_by 78",
                "description": "description 78",
                "created_at": "created_at 78",
                "project_type": "project_type 78",
                "developers": []
        },
        {
                "id": "79",
                "project_title": "project_title 79",
                "workflow_type": "workflow_type 79",
                "created_by": "created_by 79",
                "description": "description 79",
                "created_at": "created_at 79",
                "project_type": "project_type 79",
                "developers": []
        },
        {
                "id": "80",
                "project_title": "project_title 80",
                "workflow_type": "workflow_type 80",
                "created_by": "created_by 80",
                "description": "description 80",
                "created_at": "created_at 80",
                "project_type": "project_type 80",
                "developers": []
        },
        {
                "id": "81",
                "project_title": "project_title 81",
                "workflow_type": "workflow_type 81",
                "created_by": "created_by 81",
                "description": "description 81",
                "created_at": "created_at 81",
                "project_type": "project_type 81",
                "developers": []
        },
        {
                "id": "82",
                "project_title": "project_title 82",
                "workflow_type": "workflow_type 82",
                "created_by": "created_by 82",
                "description": "description 82",
                "created_at": "created_at 82",
                "project_type": "project_type 82",
                "developers": []
        },
        {
                "id": "83",
                "project_title": "project_title 83",
                "workflow_type": "workflow_type 83",
                "created_by": "created_by 83",
                "description": "description 83",
                "created_at": "created_at 83",
                "project_type": "project_type 83",
                "developers": []
        },
        {
                "id": "84",
                "project_title": "project_title 84",
                "workflow_type": "workflow_type 84",
                "created_by": "created_by 84",
                "description": "description 84",
                "created_at": "created_at 84",
                "project_type": "project_type 84",
                "developers": []
        },
        {
                "id": "85",
                "project_title": "project_title 85",
                "workflow_type": "workflow_type 85",
                "created_by": "created_by 85",
                "description": "description 85",
                "created_at": "created_at 85",
                "project_type": "project_type 85",
                "developers": []
        },
        {
                "id": "86",
                "project_title": "project_title 86",
                "workflow_type": "workflow_type 86",
                "created_by": "created_by 86",
                "description": "description 86",
                "created_at": "created_at 86",
                "project_type": "project_type 86",
                "developers": []
        },
        {
                "id": "87",
                "project_title": "project_title 87",
                "workflow_type": "workflow_type 87",
                "created_by": "created_by 87",
                "description": "description 87",
                "created_at": "created_at 87",
                "project_type": "project_type 87",
                "developers": []
        },
        {
                "id": "88",
                "project_title": "project_title 88",
                "workflow_type": "workflow_type 88",
                "created_by": "created_by 88",
                "description": "description 88",
                "created_at": "created_at 88",
                "project_type": "project_type 88",
                "developers": []
        },
        {
                "id": "89",
                "project_title": "project_title 89",
                "workflow_type": "workflow_type 89",
                "created_by": "created_by 89",
                "description": "description 89",
                "created_at": "created_at 89",
                "project_type": "project_type 89",
                "developers": []
        },
        {
                "id": "90",
                "project_title": "project_title 90",
                "workflow_type": "workflow_type 90",
                "created_by": "created_by 90",
                "description": "description 90",
                "created_at": "created_at 90",
                "project_type": "project_type 90",
                "developers": []
        },
        {
                "id": "91",
                "project_title": "project_title 91",
                "workflow_type": "workflow_type 91",
                "created_by": "created_by 91",
                "description": "description 91",
                "created_at": "created_at 91",
                "project_type": "project_type 91",
                "developers": []
        },
        {
                "id": "92",
                "project_title": "project_title 92",
                "workflow_type": "workflow_type 92",
                "created_by": "created_by 92",
                "description": "description 92",
                "created_at": "created_at 92",
                "project_type": "project_type 92",
                "developers": []
        },
        {
                "id": "93",
                "project_title": "project_title 93",
                "workflow_type": "workflow_type 93",
                "created_by": "created_by 93",
                "description": "description 93",
                "created_at": "created_at 93",
                "project_type": "project_type 93",
                "developers": []
        },
        {
                "id": "94",
                "project_title": "project_title 94",
                "workflow_type": "workflow_type 94",
                "created_by": "created_by 94",
                "description": "description 94",
                "created_at": "created_at 94",
                "project_type": "project_type 94",
                "developers": []
        },
        {
                "id": "95",
                "project_title": "project_title 95",
                "workflow_type": "workflow_type 95",
                "created_by": "created_by 95",
                "description": "description 95",
                "created_at": "created_at 95",
                "project_type": "project_type 95",
                "developers": []
        },
        {
                "id": "96",
                "project_title": "project_title 96",
                "workflow_type": "workflow_type 96",
                "created_by": "created_by 96",
                "description": "description 96",
                "created_at": "created_at 96",
                "project_type": "project_type 96",
                "developers": []
        },
        {
                "id": "97",
                "project_title": "project_title 97",
                "workflow_type": "workflow_type 97",
                "created_by": "created_by 97",
                "description": "description 97",
                "created_at": "created_at 97",
                "project_type": "project_type 97",
                "developers": []
        },
        {
                "id": "98",
                "project_title": "project_title 98",
                "workflow_type": "workflow_type 98",
                "created_by": "created_by 98",
                "description": "description 98",
                "created_at": "created_at 98",
                "project_type": "project_type 98",
                "developers": []
        },
        {
                "id": "99",
                "project_title": "project_title 99",
                "workflow_type": "workflow_type 99",
                "created_by": "created_by 99",
                "description": "description 99",
                "created_at": "created_at 99",
                "project_type": "project_type 99",
                "developers": []
        },
        {
                "id": "100",
                "project_title": "project_title 100",
                "workflow_type": "workflow_type 100",
                "created_by": "created_by 100",
                "description": "description 100",
                "created_at": "created_at 100",
                "project_type": "project_type 100",
                "developers": []
        }
]